architek/__init__.py
architek/cli.py
architek-0.7.dist-info/METADATA
architek-0.7.dist-info/WHEEL
architek-0.7.dist-info/entry_points.txt
architek-0.7.dist-info/top_level.txt
architek-0.7.dist-info/RECORD
