Metadata-Version: 2.4
Name: architek
Version: 0.7
Summary: Ferramenta CLI para criar estrutura de projetos.
Author: Luis Costa
Classifier: Programming Language :: Python :: 3
Classifier: License :: OSI Approved :: MIT License
Requires-Dist: colorama
Dynamic: author
Dynamic: classifier
Dynamic: description
Dynamic: description-content-type
Dynamic: requires-dist
Dynamic: summary
